django_oss_storage/__init__.py
django_oss_storage/backends.py
django_oss_storage/defaults.py
django_oss_storage_v2-2.0.1.dist-info/LICENSE
django_oss_storage_v2-2.0.1.dist-info/METADATA
django_oss_storage_v2-2.0.1.dist-info/WHEEL
django_oss_storage_v2-2.0.1.dist-info/top_level.txt
django_oss_storage_v2-2.0.1.dist-info/RECORD
